[{"groupId":620601,"speciality":"АСОИ","specialityId":1,"writeBook":{"semester":[{"mark":9,"subject":{"name":"Матем","id":1}}],"budget":true,"id":1},"roleDTO":"STUDENT","password":"$2a$10$kh34FbOV15ejvePm/18s3.ksucmdYsHxkurCS0fgW.xWGFBZZXQri","login":"den","name":"Павел","id":5},{"groupId":620601,"speciality":"АСОИ","specialityId":1,"writeBook":{"semester":[{"mark":9,"subject":{"name":"Философия","id":3}}],"budget":false,"id":3},"roleDTO":"STUDENT","password":"$2a$10$o3ewZlSLlTWURS2C6dwmJe0CTmAvLD1Pwgk9bsvKTtbnDzi9IGAs.","login":"max","name":"Максим","id":10}]